gradientdrift/__init__.py
gradientdrift/data/__init__.py
gradientdrift/data/batch.py
gradientdrift/data/dataset.py
gradientdrift/models/__init__.py
gradientdrift/models/garch.py
gradientdrift/models/model.py
gradientdrift/models/var.py
gradientdrift-0.2.0.dist-info/licenses/LICENSE
gradientdrift-0.2.0.dist-info/METADATA
gradientdrift-0.2.0.dist-info/WHEEL
gradientdrift-0.2.0.dist-info/top_level.txt
gradientdrift-0.2.0.dist-info/RECORD
