Metadata-Version: 2.4
Name: gradientdrift
Version: 0.2.0
Summary: GradientDrift uses JAX to fit econometric models on datasets that do not fit in memory.
Author: Philippe Debie
License-Expression: MIT
Project-URL: Homepage, https://github.com/philippe554/gradientdrift
Project-URL: Source, https://github.com/philippe554/gradientdrift
Project-URL: Tracker, https://github.com/philippe554/gradientdrift/issues
Classifier: Development Status :: 4 - Beta
Classifier: Intended Audience :: End Users/Desktop
Classifier: Programming Language :: Python :: 3
Classifier: Programming Language :: Python :: 3.10
Classifier: Programming Language :: Python :: 3.11
Classifier: Programming Language :: Python :: 3.12
Classifier: Programming Language :: Python :: 3.13
Classifier: Operating System :: OS Independent
Classifier: Topic :: Utilities
Classifier: Environment :: Console
Requires-Python: >=3.10
License-File: LICENSE
Requires-Dist: jax>=0.4.34
Requires-Dist: optax>=0.2.4
Requires-Dist: numpy>=1.24.1
Dynamic: license-file
